qextract/__init__.py
qextract/utils.py
qextract-0.0.6.data/scripts/extract_participle_phrases
qextract-0.0.6.data/scripts/extract_subordinate_clauses
qextract-0.0.6.dist-info/DESCRIPTION.rst
qextract-0.0.6.dist-info/METADATA
qextract-0.0.6.dist-info/RECORD
qextract-0.0.6.dist-info/WHEEL
qextract-0.0.6.dist-info/metadata.json
qextract-0.0.6.dist-info/top_level.txt
