Metadata-Version: 2.0
Name: qextract
Version: 0.0.6
Summary: Extract different types of phrases and clauses from text
Home-page: https://github.com/empirical-org/Quill-NLP-Tools-and-Datasets
Author: Quill.org
Author-email: max@quill.org
License: MIT
Platform: UNKNOWN
Requires-Dist: spacy
